lafmapi/__init__.py
lafmapi/api.py
lafmapi/artist.py
lafmapi/errors.py
lafmapi/music.py
lafmapi/user.py
lafmapi-0.1.0.dist-info/LICENSE
lafmapi-0.1.0.dist-info/METADATA
lafmapi-0.1.0.dist-info/WHEEL
lafmapi-0.1.0.dist-info/top_level.txt
lafmapi-0.1.0.dist-info/RECORD
