Metadata-Version: 2.1
Name: lafmapi
Version: 0.1.0
Summary: Python wrapper for the Last.fm API
Home-page: https://github.com/Gaming552/lastfm-api-wrapper
Author: cryart
Author-email: dunariibot@gmail.com
License: MIT
Keywords: lastfm api wrapper
Platform: UNKNOWN
Classifier: Development Status :: 3 - Alpha
Classifier: Intended Audience :: Developers
Classifier: License :: OSI Approved :: MIT License
Classifier: Programming Language :: Python :: 3
Classifier: Programming Language :: Python :: 3.6
Classifier: Programming Language :: Python :: 3.7
Classifier: Programming Language :: Python :: 3.8
Classifier: Programming Language :: Python :: 3.9
Requires-Python: >=3.6
License-File: LICENSE
Requires-Dist: requests
